Metadata-Version: 2.1
Name: smallscript
Version: 0.3.4
Summary: smallscript
Home-page: https://github.com/vitalstarorg/smallscript
Author: Man Chan
Author-email: man.chan@gmail.com
Classifier: Programming Language :: Python :: 3
Classifier: License :: OSI Approved :: Apache Software License
Classifier: Operating System :: OS Independent
License-File: LICENSE
Requires-Dist: antlr4-python3-runtime
Requires-Dist: graphviz
